VeilPy/__init__.py
VeilPy/setup.py
VeilPy-0.1.1.dist-info/LICENSE.txt
VeilPy-0.1.1.dist-info/METADATA
VeilPy-0.1.1.dist-info/WHEEL
VeilPy-0.1.1.dist-info/top_level.txt
VeilPy-0.1.1.dist-info/RECORD
